docs/Makefile
docs/authors.rst
docs/conf.py
docs/contributing.rst
docs/history.rst
docs/index.rst
docs/installation.rst
docs/intro.rst
docs/make.bat
docs/modules.rst
docs/roachcase.rst
docs/usage.rst
docs/img/roachcase.png
roachcase/__init__.py
roachcase/_controller.py
roachcase/_entities.py
roachcase/_repositories.py
roachcase/_version.py
roachcase/_infrastructure/__init__.py
roachcase/_infrastructure/cli.py
roachcase/_infrastructure/shelf_repositories.py
roachcase/_usecases/__init__.py
roachcase/_usecases/factories.py
roachcase/_usecases/manage_players.py
tests/__init__.py
tests/fixtures.py
tests/test_api.py
tests/test_controller.py
tests/test_entities.py
tests/test_repositories.py
tests/test_roachcase.py
tests/infrastructure/test_shelf_repositories.py
tests/usecases/test_factories.py
tests/usecases/test_manage_players.py
roachcase-0.3.5.dist-info/AUTHORS.rst
roachcase-0.3.5.dist-info/LICENSE
roachcase-0.3.5.dist-info/METADATA
roachcase-0.3.5.dist-info/WHEEL
roachcase-0.3.5.dist-info/entry_points.txt
roachcase-0.3.5.dist-info/top_level.txt
roachcase-0.3.5.dist-info/RECORD
