Metadata-Version: 2.1
Name: roachcase
Version: 0.3.5
Summary: A match making algorithm to create balanced teams from players with different skills.
Author-email: Stefano Berri <s.berri@gmail.com>
Maintainer-email: Stefano Berri <s.berri@gmail.com>
Project-URL: Documentation, https://roachcase.readthedocs.org
Project-URL: Repository, https://github.com/stefanoberri/roachcase
Keywords: games,ladder,match making
Classifier: Development Status :: 1 - Planning
Classifier: Environment :: Console
Classifier: Intended Audience :: Developers
Classifier: License :: OSI Approved :: GNU General Public License v3 (GPLv3)
Classifier: Natural Language :: English
Classifier: Operating System :: MacOS :: MacOS X
Classifier: Operating System :: POSIX :: Linux
Classifier: Programming Language :: Python :: 3.8
Classifier: Programming Language :: Python :: 3.9
Classifier: Programming Language :: Python :: 3.10
Classifier: Programming Language :: Python :: 3.11
Classifier: Programming Language :: Python :: 3.12
Classifier: Topic :: Games/Entertainment
Requires-Python: >=3.8
License-File: LICENSE
License-File: AUTHORS.rst
Requires-Dist: importlib-metadata
